LICENSE
MANIFEST.in
README.rst
setup.py
TerminalApi/__init__.py
TerminalApi/lazy.py
TerminalApi/test.py
TerminalApi/src/__init__.py
TerminalApi/src/base_url/__init__.py
TerminalApi/src/base_url/base_url.py
TerminalApi/src/batch_operation/__init__.py
TerminalApi/src/batch_operation/batch_operation.py
TerminalApi/src/create_launch/__init__.py
TerminalApi/src/create_launch/create_launch.py
TerminalApi/src/create_task/__init__.py
TerminalApi/src/create_task/create_task.py
TerminalApi/src/delete_task/__init__.py
TerminalApi/src/delete_task/delete_task.py
TerminalApi/src/download_file/__init__.py
TerminalApi/src/download_file/download_file.py
TerminalApi/src/download_task_file/__init__.py
TerminalApi/src/download_task_file/download_task_file.py
TerminalApi/src/enter_leave_maintenance_mode/__init__.py
TerminalApi/src/enter_leave_maintenance_mode/enter_leave_maintenance_mode.py
TerminalApi/src/error_codes/__init__.py
TerminalApi/src/error_codes/error_codes.py
TerminalApi/src/event_bus/__init__.py
TerminalApi/src/event_bus/event_bus.py
TerminalApi/src/execute_cleanup/__init__.py
TerminalApi/src/execute_cleanup/execute_cleanup.py
TerminalApi/src/get_doc/__init__.py
TerminalApi/src/get_doc/get_doc.py
TerminalApi/src/kill_task/__init__.py
TerminalApi/src/kill_task/kill_task.py
TerminalApi/src/lauch_task/__init__.py
TerminalApi/src/lauch_task/lauch_task.py
TerminalApi/src/list_files/__init__.py
TerminalApi/src/list_files/list_files.py
TerminalApi/src/lock_files/__init__.py
TerminalApi/src/lock_files/lock_files.py
TerminalApi/src/login/__init__.py
TerminalApi/src/login/login.py
TerminalApi/src/logout/__init__.py
TerminalApi/src/logout/logout.py
TerminalApi/src/query_tasks/__init__.py
TerminalApi/src/query_tasks/query.py
TerminalApi/src/real_time_output/__init__.py
TerminalApi/src/real_time_output/real_time_output.py
TerminalApi/src/retrieve_final_output/__init__.py
TerminalApi/src/retrieve_final_output/retrieve_final_output.py
TerminalApi/src/server_inspection/__init__.py
cmdline_mlgridengine_lazy.egg-info/PKG-INFO
cmdline_mlgridengine_lazy.egg-info/SOURCES.txt
cmdline_mlgridengine_lazy.egg-info/dependency_links.txt
cmdline_mlgridengine_lazy.egg-info/entry_points.txt
cmdline_mlgridengine_lazy.egg-info/requires.txt
cmdline_mlgridengine_lazy.egg-info/top_level.txt