Metadata-Version: 1.0
Name: cmdline-mlgridengine-lazy
Version: 0.0.6
Summary: Python command line application for mlgridengine.
Home-page: https://github.com/ligengen/lazy-cmdline-tool
Author: RootLee
Author-email: ligen_thu@163.com
License: UNKNOWN
Platform: UNKNOWN
